README.md
setup.cfg
setup.py
distributions_khalevy/Binomialdistribution.py
distributions_khalevy/Gaussiandistribution.py
distributions_khalevy/Generaldistribution.py
distributions_khalevy/__init__.py
distributions_khalevy.egg-info/PKG-INFO
distributions_khalevy.egg-info/SOURCES.txt
distributions_khalevy.egg-info/dependency_links.txt
distributions_khalevy.egg-info/not-zip-safe
distributions_khalevy.egg-info/top_level.txt